CHANGES.txt
LICENSE.txt
README.txt
setup.py
js/__init__.py
js.jquery_markitup.egg-info/PKG-INFO
js.jquery_markitup.egg-info/SOURCES.txt
js.jquery_markitup.egg-info/dependency_links.txt
js.jquery_markitup.egg-info/entry_points.txt
js.jquery_markitup.egg-info/namespace_packages.txt
js.jquery_markitup.egg-info/not-zip-safe
js.jquery_markitup.egg-info/requires.txt
js.jquery_markitup.egg-info/top_level.txt
js/jquery_markitup/__init__.py
js/jquery_markitup/resources/README.txt
js/jquery_markitup/resources/images/body.png
js/jquery_markitup/resources/images/jaysalvat.png
js/jquery_markitup/resources/images/markitup.png
js/jquery_markitup/resources/images/style.css
js/jquery_markitup/resources/markitup/jquery.markitup.js
js/jquery_markitup/resources/markitup/sets/default/set.js
js/jquery_markitup/resources/markitup/sets/default/style.css
js/jquery_markitup/resources/markitup/sets/default/images/bold.png
js/jquery_markitup/resources/markitup/sets/default/images/clean.png
js/jquery_markitup/resources/markitup/sets/default/images/image.png
js/jquery_markitup/resources/markitup/sets/default/images/italic.png
js/jquery_markitup/resources/markitup/sets/default/images/link.png
js/jquery_markitup/resources/markitup/sets/default/images/list-bullet.png
js/jquery_markitup/resources/markitup/sets/default/images/list-numeric.png
js/jquery_markitup/resources/markitup/sets/default/images/picture.png
js/jquery_markitup/resources/markitup/sets/default/images/preview.png
js/jquery_markitup/resources/markitup/sets/default/images/stroke.png
js/jquery_markitup/resources/markitup/skins/markitup/style.css
js/jquery_markitup/resources/markitup/skins/markitup/images/bg-container.png
js/jquery_markitup/resources/markitup/skins/markitup/images/bg-editor-bbcode.png
js/jquery_markitup/resources/markitup/skins/markitup/images/bg-editor-dotclear.png
js/jquery_markitup/resources/markitup/skins/markitup/images/bg-editor-html.png
js/jquery_markitup/resources/markitup/skins/markitup/images/bg-editor-json.png
js/jquery_markitup/resources/markitup/skins/markitup/images/bg-editor-markdown.png
js/jquery_markitup/resources/markitup/skins/markitup/images/bg-editor-textile.png
js/jquery_markitup/resources/markitup/skins/markitup/images/bg-editor-wiki.png
js/jquery_markitup/resources/markitup/skins/markitup/images/bg-editor-xml.png
