Metadata-Version: 1.0
Name: js.jquery-markitup
Version: 1.1.10-1
Summary: Fanstatic packaging of markitup
Home-page: https://github.com/do3cc/js.jquery_markitup
Author: Fanstatic Developers
Author-email: fanstatic@googlegroups.com
License: UNKNOWN
Platform: UNKNOWN
